[{"class_name": "text", "bbox": "1089 1128 1299 1217", "used": false}, {"class_name": "text", "bbox": "1746 1063 1925 1137", "used": false}, {"class_name": "text", "bbox": "2245 1144 2423 1237", "used": false}, {"class_name": "text", "bbox": "2419 1528 2562 1607", "used": false}, {"class_name": "text", "bbox": "1103 1611 1293 1840", "used": false}, {"class_name": "arrow", "bbox": "2301 626 2337 943", "used": false}, {"class_name": "arrow", "bbox": "1576 1149 2081 1222", "used": false}, {"class_name": "arrow", "bbox": "1170 1298 1210 1557", "used": false}, {"class_name": "arrow", "bbox": "2271 1391 2313 1750", "used": false}, {"class_name": "arrow", "bbox": "1149 1873 2137 2002", "used": false}, {"class_name": "connection", "bbox": "2231 423 2438 621", "used": false}, {"class_name": "connection", "bbox": "2181 1786 2469 2058", "used": false}, {"class_name": "decision", "bbox": "2091 974 2613 1406", "used": false}, {"class_name": "process", "bbox": "889 1034 1556 1299", "used": false}, {"class_name": "process", "bbox": "907 1564 1535 1879", "used": false}]