[{"class_name": "text", "bbox": "307 159 360 177", "used": true}, {"class_name": "text", "bbox": "46 191 73 211", "used": true}, {"class_name": "text", "bbox": "124 194 171 208", "used": true}, {"class_name": "text", "bbox": "229 198 258 209", "used": true}, {"class_name": "text", "bbox": "297 195 301 200", "used": false}, {"class_name": "text", "bbox": "248 247 253 254", "used": false}, {"class_name": "text", "bbox": "303 245 351 262", "used": true}, {"class_name": "arrow", "bbox": "84 198 106 205", "used": true}, {"class_name": "arrow", "bbox": "177 201 208 207", "used": true}, {"class_name": "arrow", "bbox": "271 177 328 205", "used": true}, {"class_name": "arrow", "bbox": "240 223 287 258", "used": true}, {"class_name": "data", "bbox": "289 151 376 178", "used": true}, {"class_name": "data", "bbox": "106 186 182 215", "used": true}, {"class_name": "data", "bbox": "284 239 362 265", "used": true}, {"class_name": "decision", "bbox": "212 183 270 222", "used": true}, {"class_name": "terminator", "bbox": "39 186 81 214", "used": true}]