[{"class_name": "text", "bbox": "1607 778 1883 869", "used": false}, {"class_name": "text", "bbox": "1592 1124 1939 1259", "used": false}, {"class_name": "text", "bbox": "1597 1532 1969 1634", "used": false}, {"class_name": "arrow", "bbox": "1693 565 1747 741", "used": false}, {"class_name": "arrow", "bbox": "1713 923 1768 1071", "used": false}, {"class_name": "arrow", "bbox": "1765 1287 1814 1488", "used": false}, {"class_name": "arrow", "bbox": "1757 1669 1820 1918", "used": false}, {"class_name": "connection", "bbox": "1631 421 1768 559", "used": false}, {"class_name": "connection", "bbox": "1701 1908 1862 2056", "used": false}, {"class_name": "data", "bbox": "1450 720 2033 931", "used": false}, {"class_name": "data", "bbox": "1422 1466 2081 1700", "used": false}, {"class_name": "process", "bbox": "1492 1064 1987 1303", "used": false}]