<?xml version="1.0" encoding="utf-8"?>
<offlineAnnotation>
  <registration>
    <markers>
      <point x="524.082368" y="399.949866" />
      <point x="2979.031629" y="404.063731" />
      <point x="2974.906952" y="2091.056819" />
      <point x="515.932675" y="2086.936209" />
    </markers>
    <frameOffset>26.6249789522624</frameOffset>
    <scale>0.191453989469007</scale>
    <translation>550.707346952262 426.574844952262</translation>
    <rotation>0.00265683672805394 550.707346952262 426.574844952262</rotation>
  </registration>
  <symbols>
    <symbol id="0" name="text">
      <bounds x="683" y="804" width="309" height="125" />
      <textMeaning>Read $n$</textMeaning>
    </symbol>
    <symbol id="1" name="text">
      <bounds x="1640" y="691" width="338" height="352" />
      <textMeaning>$T[1]=1$\\$T[2]=1$\\$i=3$</textMeaning>
    </symbol>
    <symbol id="2" name="text">
      <bounds x="667" y="1488" width="391" height="136" />
      <textMeaning>Print T[n]</textMeaning>
    </symbol>
    <symbol id="3" name="text">
      <bounds x="1332" y="1355" width="37" height="82" />
      <textMeaning>0</textMeaning>
    </symbol>
    <symbol id="4" name="text">
      <bounds x="1786" y="1359" width="181" height="112" />
      <textMeaning>$i&lt;n$</textMeaning>
    </symbol>
    <symbol id="5" name="text">
      <bounds x="2001" y="1587" width="7" height="63" />
      <textMeaning>1</textMeaning>
    </symbol>
    <symbol id="6" name="text">
      <bounds x="2682" y="1325" width="159" height="96" />
      <textMeaning>$i++$</textMeaning>
    </symbol>
    <symbol id="7" name="text">
      <bounds x="1578" y="1785" width="819" height="124" />
      <textMeaning>$T[i]=T[i-1]+T[i-2]$</textMeaning>
    </symbol>
    <symbol id="8" name="arrow">
      <bounds x="849" y="548" width="68" height="210" />
      <arrowAnnotation>
        <headBounds x="849" y="700" width="68" height="58" />
        <from x="880" y="548" />
        <to x="868" y="757" />
      </arrowAnnotation>
    </symbol>
    <symbol id="9" name="arrow">
      <bounds x="1079" y="819" width="498" height="84" />
      <arrowAnnotation>
        <headBounds x="1520" y="819" width="57" height="84" />
        <from x="1080" y="890" />
        <to x="1573" y="858" />
      </arrowAnnotation>
    </symbol>
    <symbol id="10" name="arrow">
      <bounds x="1828" y="1100" width="83" height="176" />
      <arrowAnnotation>
        <headBounds x="1828" y="1222" width="83" height="54" />
        <from x="1870" y="1100" />
        <to x="1862" y="1275" />
      </arrowAnnotation>
    </symbol>
    <symbol id="11" name="arrow">
      <bounds x="809" y="1670" width="71" height="260" />
      <arrowAnnotation>
        <headBounds x="809" y="1878" width="71" height="52" />
        <from x="836" y="1670" />
        <to x="835" y="1929" />
      </arrowAnnotation>
    </symbol>
    <symbol id="12" name="arrow">
      <bounds x="1148" y="1459" width="512" height="81" />
      <arrowAnnotation>
        <headBounds x="1148" y="1459" width="75" height="80" />
        <from x="1660" y="1462" />
        <to x="1148" y="1515" />
      </arrowAnnotation>
    </symbol>
    <symbol id="13" name="arrow">
      <bounds x="1881" y="1522" width="54" height="213" />
      <arrowAnnotation>
        <headBounds x="1881" y="1665" width="54" height="70" />
        <from x="1903" y="1522" />
        <to x="1905" y="1735" />
      </arrowAnnotation>
    </symbol>
    <symbol id="14" name="arrow">
      <bounds x="2137" y="1359" width="484" height="78" />
      <arrowAnnotation>
        <headBounds x="2137" y="1359" width="62" height="78" />
        <from x="2621" y="1364" />
        <to x="2137" y="1407" />
      </arrowAnnotation>
    </symbol>
    <symbol id="15" name="arrow">
      <bounds x="2468" y="1451" width="330" height="420" />
      <arrowAnnotation>
        <headBounds x="2699" y="1451" width="99" height="47" />
        <from x="2468" y="1870" />
        <to x="2751" y="1451" />
      </arrowAnnotation>
    </symbol>
    <symbol id="16" name="connection">
      <bounds x="834" y="427" width="95" height="121" />
    </symbol>
    <symbol id="17" name="connection">
      <bounds x="780" y="1931" width="139" height="133" />
    </symbol>
    <symbol id="18" name="data">
      <bounds x="549" y="767" width="600" height="218" />
    </symbol>
    <symbol id="19" name="data">
      <bounds x="552" y="1421" width="588" height="243" />
    </symbol>
    <symbol id="20" name="decision">
      <bounds x="1658" y="1276" width="510" height="241" />
    </symbol>
    <symbol id="21" name="process">
      <bounds x="1593" y="643" width="520" height="455" />
    </symbol>
    <symbol id="22" name="process">
      <bounds x="2618" y="1268" width="332" height="180" />
    </symbol>
    <symbol id="23" name="process">
      <bounds x="1482" y="1718" width="991" height="267" />
    </symbol>
  </symbols>
  <relations>
    <relation id="0" arity="3" name="arrow_connection">
      <symbolView symbolDataRef="8" />
      <symbolView symbolDataRef="16" connectionPoint="bottom" />
      <symbolView symbolDataRef="18" connectionPoint="top" />
    </relation>
    <relation id="1" arity="3" name="arrow_connection">
      <symbolView symbolDataRef="9" />
      <symbolView symbolDataRef="18" connectionPoint="right" />
      <symbolView symbolDataRef="21" connectionPoint="left" />
    </relation>
    <relation id="2" arity="3" name="arrow_connection">
      <symbolView symbolDataRef="10" />
      <symbolView symbolDataRef="21" connectionPoint="bottom" />
      <symbolView symbolDataRef="20" connectionPoint="top" />
    </relation>
    <relation id="3" arity="3" name="arrow_connection">
      <symbolView symbolDataRef="11" />
      <symbolView symbolDataRef="19" connectionPoint="bottom" />
      <symbolView symbolDataRef="17" connectionPoint="top" />
    </relation>
    <relation id="4" arity="3" name="arrow_connection">
      <symbolView symbolDataRef="12" />
      <symbolView symbolDataRef="20" connectionPoint="left" />
      <symbolView symbolDataRef="19" connectionPoint="right" />
    </relation>
    <relation id="5" arity="3" name="arrow_connection">
      <symbolView symbolDataRef="13" />
      <symbolView symbolDataRef="20" connectionPoint="bottom" />
      <symbolView symbolDataRef="23" connectionPoint="top" />
    </relation>
    <relation id="6" arity="3" name="arrow_connection">
      <symbolView symbolDataRef="14" />
      <symbolView symbolDataRef="22" connectionPoint="left" />
      <symbolView symbolDataRef="20" connectionPoint="right" />
    </relation>
    <relation id="7" arity="3" name="arrow_connection">
      <symbolView symbolDataRef="15" />
      <symbolView symbolDataRef="23" connectionPoint="right" />
      <symbolView symbolDataRef="22" connectionPoint="bottom" />
    </relation>
    <relation id="8" arity="2" name="text_inside">
      <symbolView symbolDataRef="0" />
      <symbolView symbolDataRef="18" />
    </relation>
    <relation id="9" arity="2" name="text_inside">
      <symbolView symbolDataRef="1" />
      <symbolView symbolDataRef="21" />
    </relation>
    <relation id="10" arity="2" name="text_inside">
      <symbolView symbolDataRef="2" />
      <symbolView symbolDataRef="19" />
    </relation>
    <relation id="11" arity="2" name="arrow_label">
      <symbolView symbolDataRef="3" />
      <symbolView symbolDataRef="12" />
    </relation>
    <relation id="12" arity="2" name="text_inside">
      <symbolView symbolDataRef="4" />
      <symbolView symbolDataRef="20" />
    </relation>
    <relation id="13" arity="2" name="arrow_label">
      <symbolView symbolDataRef="5" />
      <symbolView symbolDataRef="13" />
    </relation>
    <relation id="14" arity="2" name="text_inside">
      <symbolView symbolDataRef="6" />
      <symbolView symbolDataRef="22" />
    </relation>
    <relation id="15" arity="2" name="text_inside">
      <symbolView symbolDataRef="7" />
      <symbolView symbolDataRef="23" />
    </relation>
  </relations>
</offlineAnnotation>